{
  "tb_comics": [
    {
      "PutRequest": {
        "Item": {
          "PK": {
            "S": "CHARACTER#greenlantern"
          },
          "SK": {
            "S": "PROFILE#greenlantern"
          },
          "nickname": {
            "S": "greenlantern"
          },
          "name": {
            "S": "Green Lantern"
          },
          "real_name": {
            "S": "Hal Jordan"
          },
          "description": {
            "S": "Harold 'Hal' Jordan, one of the characters known as Green Lantern, is a superhero appearing in American comic books published by DC Comics."
          },
          "age": {
            "N": "28"
          }
        }
      }
    },
    {
      "PutRequest": {
        "Item": {
          "PK": {
            "S": "CHARACTER#batman"
          },
          "SK": {
            "S": "PROFILE#batman"
          },
          "nickname": {
            "S": "batman"
          },
          "name": {
            "S": "Batman"
          },
          "real_name": {
            "S": "Bruce Wayne"
          },
          "description": {
            "S": "Batman is a superhero appearing in American comic books published by DC Comics.Batman is a superhero appearing in American comic books published by DC Comics."
          },
          "age": {
            "N": "28"
          }
        }
      }
    },
    {
      "PutRequest": {
        "Item": {
          "PK": {
            "S": "CHARACTER#greenlantern"
          },
          "SK": {
            "S": "COMIC#ac285877"
          },
          "type": {
            "S": "COMIC"
          },
          "nickname": {
            "S": "greenlantern"
          },
          "comic_id": {
            "S": "ac285877"
          },
          "title": {
            "S": "Green Lantern: Earth One"
          },
          "description": {
            "S": "In the newest installment of the hit Earth One original graphic novel line, creators Gabriel Hardman and Corinna Bechko (Invisible Republic, Star Wars: Legacy) reimagine Hal Jordan and the Green Lantern"
          }
        }
      }
    },
    {
      "PutRequest": {
        "Item": {
          "PK": {
            "S": "CHARACTER#greenlantern"
          },
          "SK": {
            "S": "COMIC#58f59aa1"
          },
          "type": {
            "S": "COMIC"
          },
          "nickname": {
            "S": "greenlantern"
          },
          "comic_id": {
            "S": "58f59aa1"
          },
          "title": {
            "S": "Green Lantern: New Guardians"
          },
          "description": {
            "S": "Green Lantern: New Guardians is an American comic book series originally written by Tony Bedard with art by Tyler Kirkham and Batt and published by DC Comics. The team consists of representatives of each of the Corps that tap into a particular portion of the emotional spectrum."
          }
        }
      }
    },
    {
      "PutRequest": {
        "Item": {
          "PK": {
            "S": "CHARACTER#greenlantern"
          },
          "SK": {
            "S": "COMIC#fa198289"
          },
          "type": {
            "S": "COMIC"
          },
          "nickname": {
            "S": "greenlantern"
          },
          "comic_id": {
            "S": "fa198289"
          },
          "title": {
            "S": "Green Lantern Versus Aliens"
          },
          "description": {
            "S": "Green Lantern versus Aliens is a four-issue comic book intercompany crossover mini-series published jointly by DC Comics and Dark Horse Comics monthly from September to December 2000."
          }
        }
      }
    },
    {
      "PutRequest": {
        "Item": {
          "PK": {
            "S": "CHARACTER#batman"
          },
          "SK": {
            "S": "COMIC#b48988f8"
          },
          "type": {
            "S": "COMIC"
          },
          "comic_id": {
            "S": "b48988f8"
          },
          "nickname": {
            "S": "batman"
          },
          "title": {
            "S": "Batman: The Killing Joke"
          },
          "description": {
            "S": "The Killing Joke is a 1988 DC Comics one-shot graphic novel featuring the characters Batman and the Joker written by Alan Moore and illustrated by Brian Bolland."
          }
        }
      }
    }
  ]
}